alpenhorn/__init__.py
alpenhorn/cli/__init__.py
alpenhorn/cli/cli.py
alpenhorn/cli/entry.py
alpenhorn/cli/options.py
alpenhorn/cli/acq/__init__.py
alpenhorn/cli/acq/create.py
alpenhorn/cli/acq/files.py
alpenhorn/cli/acq/list.py
alpenhorn/cli/acq/show.py
alpenhorn/cli/db/__init__.py
alpenhorn/cli/db/init.py
alpenhorn/cli/file/__init__.py
alpenhorn/cli/file/clean.py
alpenhorn/cli/file/create.py
alpenhorn/cli/file/find.py
alpenhorn/cli/file/import_.py
alpenhorn/cli/file/list.py
alpenhorn/cli/file/modify.py
alpenhorn/cli/file/show.py
alpenhorn/cli/file/state.py
alpenhorn/cli/file/sync.py
alpenhorn/cli/file/verify.py
alpenhorn/cli/group/__init__.py
alpenhorn/cli/group/autosync.py
alpenhorn/cli/group/create.py
alpenhorn/cli/group/list.py
alpenhorn/cli/group/modify.py
alpenhorn/cli/group/rename.py
alpenhorn/cli/group/show.py
alpenhorn/cli/group/sync.py
alpenhorn/cli/node/__init__.py
alpenhorn/cli/node/activate.py
alpenhorn/cli/node/autoclean.py
alpenhorn/cli/node/clean.py
alpenhorn/cli/node/create.py
alpenhorn/cli/node/deactivate.py
alpenhorn/cli/node/init.py
alpenhorn/cli/node/list.py
alpenhorn/cli/node/modify.py
alpenhorn/cli/node/rename.py
alpenhorn/cli/node/scan.py
alpenhorn/cli/node/show.py
alpenhorn/cli/node/stats.py
alpenhorn/cli/node/sync.py
alpenhorn/cli/node/verify.py
alpenhorn/common/__init__.py
alpenhorn/common/config.py
alpenhorn/common/extensions.py
alpenhorn/common/logger.py
alpenhorn/common/metrics.py
alpenhorn/common/util.py
alpenhorn/daemon/__init__.py
alpenhorn/daemon/auto_import.py
alpenhorn/daemon/entry.py
alpenhorn/daemon/querywalker.py
alpenhorn/daemon/update.py
alpenhorn/db/__init__.py
alpenhorn/db/_base.py
alpenhorn/db/acquisition.py
alpenhorn/db/archive.py
alpenhorn/db/data_index.py
alpenhorn/db/storage.py
alpenhorn/io/__init__.py
alpenhorn/io/_default_asyncs.py
alpenhorn/io/base.py
alpenhorn/io/default.py
alpenhorn/io/ioutil.py
alpenhorn/io/lfs.py
alpenhorn/io/lustrehsm.py
alpenhorn/io/lustrequota.py
alpenhorn/io/polling.py
alpenhorn-2.0.0rc2.dist-info/licenses/LICENSE
alpenhorn-2.0.0rc2.dist-info/METADATA
alpenhorn-2.0.0rc2.dist-info/WHEEL
alpenhorn-2.0.0rc2.dist-info/entry_points.txt
alpenhorn-2.0.0rc2.dist-info/top_level.txt
alpenhorn-2.0.0rc2.dist-info/RECORD
